seguid/__init__.py
seguid/__main__.py
seguid/_asserts.py
seguid/_chksum.py
seguid/_config.py
seguid/_manip.py
seguid/_reprutils.py
seguid/_tables.py
seguid-0.2.1.dist-info/LICENSE.txt
seguid-0.2.1.dist-info/METADATA
seguid-0.2.1.dist-info/WHEEL
seguid-0.2.1.dist-info/RECORD
