Metadata-Version: 2.3
Name: seguid
Version: 0.2.1
Summary: Sequence Globally Unique Identifier (SEGUID) Checksums for Linear, Circular, Single-Stranded and Double-Stranded Biological Sequences
License: MIT
Author: Bjorn Johansson
Author-email: bjornjobb@gmail.com
Requires-Python: >=3.6,<4.0
Classifier: License :: OSI Approved :: MIT License
Classifier: Programming Language :: Python :: 3
Classifier: Programming Language :: Python :: 3.6
Classifier: Programming Language :: Python :: 3.7
Classifier: Programming Language :: Python :: 3.8
Classifier: Programming Language :: Python :: 3.9
Classifier: Programming Language :: Python :: 3.10
Classifier: Programming Language :: Python :: 3.11
Classifier: Programming Language :: Python :: 3.12
Classifier: Programming Language :: Python :: 3.13
Provides-Extra: pydivsufsort
Requires-Dist: pydivsufsort (<=0.0.14) ; (python_version < "3.9") and (extra == "pydivsufsort")
Requires-Dist: pydivsufsort (>=0.0.18) ; (python_version >= "3.9") and (extra == "pydivsufsort")
Requires-Dist: setuptools (<=59.6.0) ; python_version < "3.7"
Requires-Dist: setuptools (<=69.0.3) ; python_version < "3.8"
Project-URL: Bug Tracker, https://github.com/seguid/seguid-python/issues
Project-URL: Documentation, https://seguid-python.seguid.org
Project-URL: Homepage, https://www.seguid.org
Project-URL: Repository, https://github.com/seguid/seguid-python
